examples/__init__.py
examples/example1.py
examples/example2.py
examples/example3.py
examples/example4.py
examples/example5.py
examples/example6.py
examples/sample_classes.py
mlforge/__init__.py
mlforge/_version.py
mlforge/logconfig.py
mlforge/mlforge.py
mlforge/progbar.py
mlforge-0.2.2.dist-info/LICENSE.txt
mlforge-0.2.2.dist-info/METADATA
mlforge-0.2.2.dist-info/WHEEL
mlforge-0.2.2.dist-info/top_level.txt
mlforge-0.2.2.dist-info/RECORD
