Metadata-Version: 2.1
Name: mlforge
Version: 0.2.2
Summary: A package to design and run sequential ML pipelines
Home-page: https://github.com/renero/mlforge
Author: J. Renero
Author-email: jesus.renero@gmail.com
Classifier: Programming Language :: Python :: 3
Classifier: License :: OSI Approved :: MIT License
Classifier: Operating System :: OS Independent
Requires-Python: >=3.6
License-File: LICENSE.txt
